{
  "id": "2Installation",
  "title": "Installation",
  "description": "Git is required for installation when going through Unity Package Manager",
  "source": "@site/docs/2Installation.md",
  "sourceDirName": ".",
  "slug": "/Installation",
  "permalink": "/laio-documentation/Installation",
  "draft": false,
  "unlisted": false,
  "tags": [],
  "version": "current",
  "frontMatter": {
    "title": "Installation",
    "slug": "/Installation"
  },
  "sidebar": "tutorialSidebar",
  "previous": {
    "title": "Overview",
    "permalink": "/laio-documentation/"
  },
  "next": {
    "title": "Benchmarking",
    "permalink": "/laio-documentation/Laio/Tools/Benchmarking"
  }
}